Metadata-Version: 1.0
Name: gaussian-probability
Version: 0.1
Summary: Gaussian distirbution
Home-page: UNKNOWN
Author: Yessy Marie
Author-email: UNKNOWN
License: UNKNOWN
Platform: UNKNOWN
